[
    {
        "id":"1",
        "image":"./images/product1.jfif",
        "title":"Trees",
        "price":"11.12",
        "Category":"Electronics"
    },
    {
        "id":"2",
        "image":"./images/left-wing-picture.jpg",
        "title":"wood",
        "price":"17.12",
        "Category":"Home Appliance"
    },
    {
        "id":"3",
        "image":"./images/img3.jpg",
        "title":"road",
        "price":"116.12",
        "Category":"Toys"
    },
    {
        "id":"4",
        "image":"./images/img2.jpg",
        "title":"river2",
        "price":"12.12",
        "Category":"Accessories"
    },
    {
        "id":"5",
        "image":"./images/img4.jpg",
        "title":"river4",
        "price":"12.12",
        "Category":"Home Appliance"
    }
    ,
    {
        "id":"7",
        "image":"./images/img4.jpg",
        "title":"river6",
        "price":"12.12",
        "Category":"Accessories"
    }
    ,
    {
        "id":"8",
        "image":"./images/img4.jpg",
        "title":"river8",
        "price":"12.12",
        "Category":"Accessories"
    }
    ,
    {
        "id":"9",
        "image":"./images/img4.jpg",
        "title":"river10",
        "price":"12.12",
        "Category":"Accessories"
    }
    ,
    {
        "id":"10",
        "image":"./images/img4.jpg",
        "title":"river15",
        "price":"12.12",
        "Category":"Home Appliance"
    }
    ,
    {
        "id":"11",
        "image":"./images/img4.jpg",
        "title":"river21",
        "price":"12.12",
        "Category":"Toys"
    }
    ,
    {
        "id":"12",
        "image":"./images/img4.jpg",
        "title":"river45",
        "price":"12.12",
        "Category":"Toys"
    }
    
]